{
    "name": "Shorty",
    "matrix": {
        "rows": 3,
        "cols": 3
    },
    "vendorId": "0x5453",
    "productId": "0x5400",
    "layouts": {
        "keymap": [
            [
                {
                    "a": 7
                },
                "e0",
                {
                    "x": 1
                },
                "e1"
            ],
            [
                {
                    "a": 4
                },
                "0,0",
                "0,1",
                "0,2"
            ],
            [
                "1,0",
                "1,1",
                "1,2"
            ],
            [
                "2,0",
                "2,1",
                "2,2"
            ]
        ]
    }
}